{
  "219810605": [
    "C_Item_Default_N",
    "C_Item_Default_N"
  ],
  "337496069": [
    "C_Item_Frame_Platinum_Rare_N",
    "C_Item_Frame_Platinum_Rare_N"
  ],
  "000103825": [
    "C_Item_Frame_MonkeyKing_Rare_N",
    "C_Item_Frame_MonkeyKing_Rare_N"
  ],
  "571710675": [
    "C_Item_Frame_PreciseShot_Rare_N",
    "C_Item_Frame_PreciseShot_Rare_N"
  ],
  "613014451": [
    "C_Item_Frame_Bulls_Rare_N",
    "C_Item_Frame_Bulls_Rare_N"
  ],
  "390425545": [
    "C_Item_Frame_Pioneer_Eipc_N",
    "C_Item_Frame_Pioneer_Eipc_N"
  ],
  "006388501": [
    "C_Item_Frame_GoldenDragon_Eipc_N",
    "C_Item_Frame_GoldenDragon_Eipc_N"
  ],
  "689821339": [
    "C_Item_Frame_PaperPlane_Rare_N",
    "C_Item_Frame_PaperPlane_Rare_N"
  ],
  "626839008": [
    "C_Item_theme_CrystalStorm_N",
    "C_Item_theme_CrystalStorm_N"
  ],
  "695141811": [
    "C_Item_Frame_HillsideEncounter_Rare_N",
    "C_Item_Frame_HillsideEncounter_Rare_N"
  ],
  "829022898": [
    "C_Item_theme_S1_N",
    "C_Item_theme_S1_N"
  ],
  "712372697": [
    "C_Item_theme_AlphaAce_N",
    "C_Item_theme_AlphaAce_N"
  ],
  "884982403": [
    "C_Item_theme_AgentAssault_N",
    "C_Item_theme_AgentAssault_N"
  ],
  "543782120": [
    "C_Item_theme_AgentAssembly_N",
    "C_Item_theme_AgentAssembly_N"
  ],
  "331743518": [
    "C_Ceneral_TypeName_C4_N",
    "C_Ceneral_TypeName_C4_N"
  ],
  "014701117": [
    "C_Item_theme_Western_N",
    "C_Item_theme_Western_N"
  ],
  "983734592": [
    "C_Item_theme_SP_N",
    "C_Item_theme_SP_N"
  ],
  "490314830": [
    "C_Item_theme_Pixels_N",
    "C_Item_theme_Pixels_N"
  ],
  "654045994": [
    "C_Item_theme_SummerActivities_N",
    "C_Item_theme_SummerActivities_N"
  ],
  "852199200": [
    "C_Item_theme_PoolParty_N",
    "C_Item_theme_PoolParty_N"
  ],
  "055149652": [
    "C_Item_theme_Constellation_N",
    "C_Item_theme_Constellation_N"
  ],
  "563736585": [
    "C_Item_theme_Daimond_N",
    "C_Item_theme_Daimond_N"
  ],
  "183804875": [
    "C_Item_theme_Transformers_N",
    "C_Item_theme_Transformers_N"
  ],
  "333644674": [
    "C_Item_theme_TidePlay_N",
    "C_Item_theme_TidePlay_N"
  ],
  "293982694": [
    "C_Item_theme_Halloween_N",
    "C_Item_theme_Halloween_N"
  ],
  "460564408": [
    "C_Item_theme_PVEBOSS_N",
    "C_Item_theme_PVEBOSS_N"
  ],
  "895907029": [
    "C_Item_theme_Christmas2022_N",
    "C_Item_theme_Christmas2022_N"
  ],
  "088029086": [
    "C_Item_theme_Neon_N",
    "C_Item_theme_Neon_N"
  ],
  "594999101": [
    "C_Item_theme_Logo_N",
    "C_Item_theme_Logo_N"
  ],
  "838055491": [
    "C_Item_theme_BrazilSoccer_N",
    "C_Item_theme_BrazilSoccer_N"
  ]
}